{"file":"power.png","frames":{
"bulletplane1":{"x":82,"y":1,"w":56,"h":55,"offX":1,"offY":1,"sourceW":57,"sourceH":57},
"bulletplane2":{"x":82,"y":1,"w":56,"h":55,"offX":1,"offY":1,"sourceW":57,"sourceH":57},
"bulletplane3":{"x":82,"y":1,"w":56,"h":55,"offX":1,"offY":1,"sourceW":57,"sourceH":57},
"bulletplane4":{"x":82,"y":1,"w":56,"h":55,"offX":1,"offY":1,"sourceW":57,"sourceH":57},
"power-b1":{"x":140,"y":50,"w":38,"h":39,"offX":4,"offY":3,"sourceW":43,"sourceH":43},
"power-b2":{"x":121,"y":91,"w":33,"h":40,"offX":3,"offY":1,"sourceW":43,"sourceH":43},
"power-b3":{"x":184,"y":1,"w":42,"h":41,"offX":1,"offY":1,"sourceW":43,"sourceH":43},
"power-b4":{"x":156,"y":94,"w":33,"h":40,"offX":6,"offY":1,"sourceW":43,"sourceH":43},
"power-bbomb":{"x":191,"y":94,"w":25,"h":27,"offX":9,"offY":7,"sourceW":43,"sourceH":43},
"power-blife":{"x":82,"y":58,"w":37,"h":37,"offX":3,"offY":4,"sourceW":43,"sourceH":43},
"power-bullet1-1":{"x":190,"y":140,"w":32,"h":33,"offX":1,"offY":0,"sourceW":33,"sourceH":33},
"power-bullet1-2":{"x":1,"y":80,"w":28,"h":33,"offX":3,"offY":0,"sourceW":33,"sourceH":33},
"power-bullet1-3":{"x":31,"y":133,"w":28,"h":31,"offX":3,"offY":0,"sourceW":33,"sourceH":33},
"power-bullet1-4":{"x":1,"y":210,"w":29,"h":33,"offX":2,"offY":0,"sourceW":33,"sourceH":33},
"power-bullet2-1":{"x":190,"y":175,"w":32,"h":33,"offX":1,"offY":0,"sourceW":33,"sourceH":33},
"power-bullet2-2":{"x":1,"y":133,"w":28,"h":33,"offX":3,"offY":0,"sourceW":33,"sourceH":33},
"power-bullet2-3":{"x":31,"y":80,"w":28,"h":31,"offX":3,"offY":0,"sourceW":33,"sourceH":33},
"power-bullet2-4":{"x":224,"y":175,"w":29,"h":33,"offX":2,"offY":0,"sourceW":33,"sourceH":33},
"power-bullet3-1":{"x":156,"y":136,"w":32,"h":33,"offX":1,"offY":0,"sourceW":33,"sourceH":33},
"power-bullet3-2":{"x":224,"y":140,"w":29,"h":33,"offX":2,"offY":0,"sourceW":33,"sourceH":33},
"power-bullet3-3":{"x":61,"y":97,"w":28,"h":29,"offX":3,"offY":2,"sourceW":33,"sourceH":33},
"power-bullet3-4":{"x":1,"y":171,"w":29,"h":32,"offX":2,"offY":0,"sourceW":33,"sourceH":33},
"power-mis1":{"x":140,"y":1,"w":42,"h":47,"offX":4,"offY":0,"sourceW":48,"sourceH":48},
"power-mis2":{"x":218,"y":92,"w":31,"h":46,"offX":10,"offY":1,"sourceW":48,"sourceH":48},
"power-mis3":{"x":184,"y":44,"w":32,"h":48,"offX":11,"offY":0,"sourceW":48,"sourceH":48},
"power-mis4":{"x":218,"y":44,"w":31,"h":46,"offX":9,"offY":2,"sourceW":48,"sourceH":48},
"power-misf":{"x":121,"y":58,"w":17,"h":20,"offX":16,"offY":14,"sourceW":48,"sourceH":48},
"power-mism":{"x":31,"y":113,"w":21,"h":18,"offX":14,"offY":14,"sourceW":48,"sourceH":48},
"store":{"x":1,"y":1,"w":79,"h":77,"offX":0,"offY":0,"sourceW":79,"sourceH":77}}}